Metadata-Version: 1.0
Name: swyt
Version: 0.0.1
Summary: A very basic Swyt
Home-page: UNKNOWN
Author: swyt.dev
Author-email: support@swyt.dev
License: MIT
Keywords: swyt
Platform: UNKNOWN
